alphacsc/__init__.py
alphacsc/_d_solver.py
alphacsc/_version.py
alphacsc/_z_encoder.py
alphacsc/convolutional_dictionary_learning.py
alphacsc/init_dict.py
alphacsc/learn_d_z.py
alphacsc/learn_d_z_mcem.py
alphacsc/learn_d_z_multi.py
alphacsc/loss_and_gradient.py
alphacsc/online_dictionary_learning.py
alphacsc/simulate.py
alphacsc/update_d.py
alphacsc/update_d_multi.py
alphacsc/update_w.py
alphacsc/update_z.py
alphacsc/update_z_multi.py
alphacsc/datasets/__init__.py
alphacsc/datasets/hcp.py
alphacsc/datasets/mne_data.py
alphacsc/datasets/simulate.py
alphacsc/other/__init__.py
alphacsc/other/motif.py
alphacsc/other/swm.py
alphacsc/tests/__init__.py
alphacsc/tests/conftest.py
alphacsc/tests/test_d_solver.py
alphacsc/tests/test_init_d.py
alphacsc/tests/test_learn_d_z.py
alphacsc/tests/test_learn_d_z_multi.py
alphacsc/tests/test_learn_d_z_weighted.py
alphacsc/tests/test_loss_and_gradient.py
alphacsc/tests/test_online_dictionary_learning.py
alphacsc/tests/test_update_d_multi.py
alphacsc/tests/test_update_z_multi.py
alphacsc/tests/test_z_encoder.py
alphacsc/utils/__init__.py
alphacsc/utils/arma.py
alphacsc/utils/compute_constants.py
alphacsc/utils/config.py
alphacsc/utils/convolution.py
alphacsc/utils/coordinate_descent.py
alphacsc/utils/dictionary.py
alphacsc/utils/optim.py
alphacsc/utils/profile_this.py
alphacsc/utils/signal.py
alphacsc/utils/validation.py
alphacsc/utils/tests/test_constants.py
alphacsc/utils/tests/test_optim.py
alphacsc/utils/tests/test_utils.py
alphacsc/utils/tests/test_validation.py
alphacsc/viz/__init__.py
alphacsc/viz/callback.py
alphacsc/viz/epoch.py
alphacsc/viz/plot_output.py
alphacsc/viz/tools.py
alphacsc-0.4.1.dist-info/LICENSE
alphacsc-0.4.1.dist-info/METADATA
alphacsc-0.4.1.dist-info/WHEEL
alphacsc-0.4.1.dist-info/top_level.txt
alphacsc-0.4.1.dist-info/zip-safe
alphacsc-0.4.1.dist-info/RECORD
