Metadata-Version: 2.1
Name: alphacsc
Version: 0.4.1
Summary: Convolutional dictionary learning for noisy signals.
Home-page: https://github.com/alphacsc/alphacsc.git
Author-email: thomas.moreau@inria.fr
Maintainer: Thomas Moreau
License: BSD (3-clause)
Platform: any
Classifier: Intended Audience :: Science/Research
Classifier: Intended Audience :: Developers
Classifier: License :: OSI Approved
Classifier: Programming Language :: Python
Classifier: Topic :: Software Development
Classifier: Topic :: Scientific/Engineering
Classifier: Operating System :: Microsoft :: Windows
Classifier: Operating System :: POSIX
Classifier: Operating System :: Unix
Classifier: Operating System :: MacOS
License-File: LICENSE
Requires-Dist: mne
Requires-Dist: numba
Requires-Dist: numpy
Requires-Dist: scipy
Requires-Dist: joblib
Requires-Dist: matplotlib
Requires-Dist: scikit-learn
Provides-Extra: dev
Requires-Dist: flake8; extra == "dev"
Provides-Extra: dicodile
Requires-Dist: dicodile>=0.2.1; extra == "dicodile"
Provides-Extra: doc
Requires-Dist: pydata-sphinx-theme; extra == "doc"
Requires-Dist: numpydoc; extra == "doc"
Requires-Dist: sphinx-gallery; extra == "doc"
Requires-Dist: sphinx; extra == "doc"
Requires-Dist: pactools; extra == "doc"
Requires-Dist: nibabel; extra == "doc"
Provides-Extra: test
Requires-Dist: pytest; extra == "test"
Requires-Dist: pytest-cov; extra == "test"
